setup.py
shantnu_joke/__init__.py
shantnu_joke/joke.py
shantnu_joke.egg-info/PKG-INFO
shantnu_joke.egg-info/SOURCES.txt
shantnu_joke.egg-info/dependency_links.txt
shantnu_joke.egg-info/top_level.txt