Metadata-Version: 1.1
Name: shantnu-joke
Version: 0.4
Summary: Shantnus terrible joke
Home-page: https://github.com/shantnu/shantnu_joke
Author: Shantnu
Author-email: UNKNOWN
License: GPL
Download-URL: https://github.com/shantnu/shantnu_joke/archive/0.4.zip
Platform: UNKNOWN
